aio_readsb/__init__.py
aio_readsb/__version__.py
aio_readsb/consts.py
aio_readsb/feed.py
aio_readsb/feed_entry.py
aio_readsb/feed_manager.py
aio_readsb/status_update.py
aio_readsb-0.1.6.dist-info/LICENSE
aio_readsb-0.1.6.dist-info/METADATA
aio_readsb-0.1.6.dist-info/WHEEL
aio_readsb-0.1.6.dist-info/top_level.txt
aio_readsb-0.1.6.dist-info/RECORD
