Metadata-Version: 2.1
Name: aio-readsb
Version: 0.1.6
Summary: An async client library for planes using information.
Home-page: https://github.com/kuchel77/python-aio-readsb
Author: Mark Kuchel
Author-email: mark@kuchel.net
License: UNKNOWN
Platform: UNKNOWN
Classifier: Programming Language :: Python :: 3.6
Classifier: Programming Language :: Python :: 3.7
Classifier: Programming Language :: Python :: 3.8
Classifier: License :: OSI Approved :: Apache Software License
Classifier: Operating System :: OS Independent
License-File: LICENSE
Requires-Dist: aiohttp (>=3.5.4)
Requires-Dist: geopy
Requires-Dist: pytz (>=2019.01)
